verysimplemodule_andreia/__init__.py
verysimplemodule_andreia/add.py
verysimplemodule_andreia/subtract.py
verysimplemodule_andreia/extra/__init__.py
verysimplemodule_andreia/extra/divide.py
verysimplemodule_andreia/extra/multiple.py
verysimplemodule_andreia-0.0.2.dist-info/METADATA
verysimplemodule_andreia-0.0.2.dist-info/WHEEL
verysimplemodule_andreia-0.0.2.dist-info/top_level.txt
verysimplemodule_andreia-0.0.2.dist-info/RECORD
